flask_monitor/__init__.py
flask_monitor/example.py
flask_monitor/metrics.py
flask_monitor/tests/__init__.py
flask_monitor/tests/conftest.py
flask_monitor/tests/test_example.py
gutorc_flask_monitor-0.0.3.dist-info/LICENSE
gutorc_flask_monitor-0.0.3.dist-info/METADATA
gutorc_flask_monitor-0.0.3.dist-info/WHEEL
gutorc_flask_monitor-0.0.3.dist-info/top_level.txt
gutorc_flask_monitor-0.0.3.dist-info/RECORD
